readstr/__init__.py
readstr/__pkginfo__.py
readstr/base64.py
readstr/readable_uuid.py
readstr/readdataclass.py
readstr/readstr.py
tests/__init__.py
tests/test_from_env_or_args.py
tests/test_readstr.py
tests/test_uuids.py
readstr-0.8.0.dist-info/LICENSE
readstr-0.8.0.dist-info/METADATA
readstr-0.8.0.dist-info/WHEEL
readstr-0.8.0.dist-info/top_level.txt
readstr-0.8.0.dist-info/RECORD
