Metadata-Version: 2.1
Name: readstr
Version: 0.8.0
Summary: Read Strings
Home-page: https://github.com/scravy/readstr
Author: Julian Fleischer
Author-email: tirednesscankill@warhog.net
License: UNKNOWN
Platform: UNKNOWN
Classifier: Programming Language :: Python :: 3
Classifier: License :: OSI Approved :: MIT License
Classifier: Operating System :: OS Independent
Requires-Python: >=3.8
